{
  "pageRequested": 1,
  "pageSize": 100,
  "pageCount": 1,
  "entries": [
    {
      "rank": 1,
      "name": "Jimpa SWE",
      "isVIP": false,
      "isFounder": false,
      "isPlayer": false,
      "isDnfEntry": false,
      "playerDiff": 0,
      "vehicleName": "Citroën C4 Rally",
      "stageTime": "04:19.822",
      "stageDiff": "--",
      "totalTime": "20:40.181",
      "totalDiff": "--",
      "nationality": "eLngSwedish"
    },
    {
      "rank": 2,
      "name": "Plog03327",
      "isVIP": false,
      "isFounder": false,
      "isPlayer": false,
      "isDnfEntry": false,
      "playerDiff": 0,
      "vehicleName": "Citroën C4 Rally",
      "stageTime": "04:21.139",
      "stageDiff": "+00:01.317",
      "totalTime": "20:51.473",
      "totalDiff": "+00:11.292",
      "nationality": "eLngSwedish"
    },
    {
      "rank": 3,
      "name": "Rally-Kalle72",
      "isVIP": false,
      "isFounder": false,
      "isPlayer": false,
      "isDnfEntry": false,
      "playerDiff": 6,
      "vehicleName": "ŠKODA Fabia Rally",
      "stageTime": "04:27.839",
      "stageDiff": "+00:08.017",
      "totalTime": "21:45.659",
      "totalDiff": "+01:05.478",
      "nationality": "eLngSwedish"
    },
    {
      "rank": 4,
      "name": "Mazzan",
      "isVIP": false,
      "isFounder": false,
      "isPlayer": false,
      "isDnfEntry": false,
      "playerDiff": 0,
      "vehicleName": "Ford Focus RS Rally 2007",
      "stageTime": "04:29.339",
      "stageDiff": "+00:09.517",
      "totalTime": "21:14.962",
      "totalDiff": "+00:34.781",
      "nationality": "eLngSwedish"
    },
    {
      "rank": 5,
      "name": "Tastan",
      "isVIP": false,
      "isFounder": false,
      "isPlayer": false,
      "isDnfEntry": false,
      "playerDiff": 3,
      "vehicleName": "SUBARU Impreza",
      "stageTime": "04:30.505",
      "stageDiff": "+00:10.683",
      "totalTime": "21:46.528",
      "totalDiff": "+01:06.347",
      "nationality": "eLngSwedish"
    },
    {
      "rank": 6,
      "name": "Lialok12",
      "isVIP": false,
      "isFounder": false,
      "isPlayer": false,
      "isDnfEntry": false,
      "playerDiff": 6,
      "vehicleName": "Ford Focus RS Rally 2007",
      "stageTime": "04:34.989",
      "stageDiff": "+00:15.167",
      "totalTime": "22:00.191",
      "totalDiff": "+01:20.010",
      "nationality": "eLngSwedish"
    },
    {
      "rank": 7,
      "name": "doktor.frojd",
      "isVIP": false,
      "isFounder": false,
      "isPlayer": false,
      "isDnfEntry": false,
      "playerDiff": -2,
      "vehicleName": "Ford Focus RS Rally 2007",
      "stageTime": "04:35.605",
      "stageDiff": "+00:15.783",
      "totalTime": "21:41.938",
      "totalDiff": "+01:01.757",
      "nationality": "eLngSwedish"
    },
    {
      "rank": 8,
      "name": "Thomasstriden",
      "isVIP": false,
      "isFounder": false,
      "isPlayer": false,
      "isDnfEntry": false,
      "playerDiff": 6,
      "vehicleName": "ŠKODA Fabia Rally",
      "stageTime": "04:38.488",
      "stageDiff": "+00:18.666",
      "totalTime": "22:43.418",
      "totalDiff": "+02:03.237",
      "nationality": "eLngSwedish"
    },
    {
      "rank": 9,
      "name": "rallyrobban81",
      "isVIP": false,
      "isFounder": false,
      "isPlayer": false,
      "isDnfEntry": false,
      "playerDiff": 4,
      "vehicleName": "Ford Focus RS Rally 2007",
      "stageTime": "04:40.555",
      "stageDiff": "+00:20.733",
      "totalTime": "22:31.659",
      "totalDiff": "+01:51.478",
      "nationality": "eLngSwedish"
    },
    {
      "rank": 10,
      "name": "Wiberg",
      "isVIP": false,
      "isFounder": false,
      "isPlayer": false,
      "isDnfEntry": false,
      "playerDiff": -3,
      "vehicleName": "Citroën C4 Rally",
      "stageTime": "04:43.822",
      "stageDiff": "+00:24.000",
      "totalTime": "21:52.166",
      "totalDiff": "+01:11.985",
      "nationality": "eLngSwedish"
    },
    {
      "rank": 11,
      "name": "Stålkrabban",
      "isVIP": false,
      "isFounder": false,
      "isPlayer": false,
      "isDnfEntry": false,
      "playerDiff": -5,
      "vehicleName": "SUBARU Impreza",
      "stageTime": "04:46.489",
      "stageDiff": "+00:26.667",
      "totalTime": "21:53.180",
      "totalDiff": "+01:12.999",
      "nationality": "eLngSwedish"
    },
    {
      "rank": 12,
      "name": "rallifan",
      "isVIP": false,
      "isFounder": false,
      "isPlayer": false,
      "isDnfEntry": false,
      "playerDiff": -9,
      "vehicleName": "SUBARU Impreza",
      "stageTime": "04:52.238",
      "stageDiff": "+00:32.416",
      "totalTime": "21:36.161",
      "totalDiff": "+00:55.980",
      "nationality": "eLngSwedish"
    },
    {
      "rank": 13,
      "name": "johan.nesse",
      "isVIP": false,
      "isFounder": false,
      "isPlayer": false,
      "isDnfEntry": false,
      "playerDiff": 2,
      "vehicleName": "ŠKODA Fabia Rally",
      "stageTime": "04:58.504",
      "stageDiff": "+00:38.682",
      "totalTime": "23:04.418",
      "totalDiff": "+02:24.237",
      "nationality": "eLngSwedish"
    },
    {
      "rank": 14,
      "name": "Stefan2002",
      "isVIP": false,
      "isFounder": false,
      "isPlayer": false,
      "isDnfEntry": true,
      "playerDiff": 2,
      "vehicleName": "SUBARU Impreza",
      "stageTime": "15:00.000",
      "stageDiff": "+10:40.178",
      "totalTime": "33:37.951",
      "totalDiff": "+12:57.770",
      "nationality": "eLngSwedish"
    },
    {
      "rank": 15,
      "name": "slim2018swe",
      "isVIP": false,
      "isFounder": false,
      "isPlayer": false,
      "isDnfEntry": true,
      "playerDiff": 5,
      "vehicleName": "SUBARU Impreza (2001)",
      "stageTime": "15:00.000",
      "stageDiff": "+10:40.178",
      "totalTime": "01:30:00.000",
      "totalDiff": "+01:09:19.819",
      "nationality": "eLngSwedish"
    },
    {
      "rank": 16,
      "name": "bjorla78",
      "isVIP": false,
      "isFounder": false,
      "isPlayer": false,
      "isDnfEntry": true,
      "playerDiff": 1,
      "vehicleName": "SUBARU Impreza",
      "stageTime": "15:00.000",
      "stageDiff": "+10:40.178",
      "totalTime": "55:57.189",
      "totalDiff": "+35:17.008",
      "nationality": "eLngSwedish"
    },
    {
      "rank": 17,
      "name": "Dyrran2",
      "isVIP": false,
      "isFounder": false,
      "isPlayer": false,
      "isDnfEntry": true,
      "playerDiff": -7,
      "vehicleName": "SUBARU Impreza",
      "stageTime": "15:00.000",
      "stageDiff": "+10:40.178",
      "totalTime": "32:17.905",
      "totalDiff": "+11:37.724",
      "nationality": "eLngSwedish"
    },
    {
      "rank": 18,
      "name": "Skåningen",
      "isVIP": false,
      "isFounder": false,
      "isPlayer": false,
      "isDnfEntry": true,
      "playerDiff": -7,
      "vehicleName": "Citroën C4 Rally",
      "stageTime": "15:00.000",
      "stageDiff": "+10:40.178",
      "totalTime": "32:24.770",
      "totalDiff": "+11:44.589",
      "nationality": "eLngSwedish"
    },
    {
      "rank": 19,
      "name": "marko68",
      "isVIP": false,
      "isFounder": false,
      "isPlayer": false,
      "isDnfEntry": true,
      "playerDiff": -1,
      "vehicleName": "ŠKODA Fabia Rally",
      "stageTime": "15:00.000",
      "stageDiff": "+10:40.178",
      "totalTime": "56:15.110",
      "totalDiff": "+35:34.929",
      "nationality": "eLngSwedish"
    },
    {
      "rank": 20,
      "name": "\\\\SWE//",
      "isVIP": false,
      "isFounder": false,
      "isPlayer": false,
      "isDnfEntry": true,
      "playerDiff": -1,
      "vehicleName": "ŠKODA Fabia Rally",
      "stageTime": "15:00.000",
      "stageDiff": "+10:40.178",
      "totalTime": "01:06:24.493",
      "totalDiff": "+45:44.312",
      "nationality": "eLngSwedish"
    }
  ]
}