{
  "pageRequested": 1,
  "pageSize": 100,
  "pageCount": 1,
  "entries": [
    {
      "rank": 1,
      "name": "Jimpa SWE",
      "isVIP": false,
      "isFounder": false,
      "isPlayer": false,
      "isDnfEntry": false,
      "playerDiff": 0,
      "vehicleName": "Citroën C4 Rally",
      "stageTime": "06:32.300",
      "stageDiff": "--",
      "totalTime": "16:20.359",
      "totalDiff": "--",
      "nationality": "eLngSwedish"
    },
    {
      "rank": 2,
      "name": "Plog03327",
      "isVIP": false,
      "isFounder": false,
      "isPlayer": false,
      "isDnfEntry": false,
      "playerDiff": 0,
      "vehicleName": "Citroën C4 Rally",
      "stageTime": "06:33.434",
      "stageDiff": "+00:01.134",
      "totalTime": "16:30.334",
      "totalDiff": "+00:09.975",
      "nationality": "eLngSwedish"
    },
    {
      "rank": 3,
      "name": "Stålkrabban",
      "isVIP": false,
      "isFounder": false,
      "isPlayer": false,
      "isDnfEntry": false,
      "playerDiff": 9,
      "vehicleName": "SUBARU Impreza",
      "stageTime": "06:34.084",
      "stageDiff": "+00:01.784",
      "totalTime": "17:06.691",
      "totalDiff": "+00:46.332",
      "nationality": "eLngSwedish"
    },
    {
      "rank": 4,
      "name": "Wiberg",
      "isVIP": false,
      "isFounder": false,
      "isPlayer": false,
      "isDnfEntry": false,
      "playerDiff": 7,
      "vehicleName": "Citroën C4 Rally",
      "stageTime": "06:38.800",
      "stageDiff": "+00:06.500",
      "totalTime": "17:08.344",
      "totalDiff": "+00:47.985",
      "nationality": "eLngSwedish"
    },
    {
      "rank": 5,
      "name": "Skåningen",
      "isVIP": false,
      "isFounder": false,
      "isPlayer": false,
      "isDnfEntry": false,
      "playerDiff": 10,
      "vehicleName": "Citroën C4 Rally",
      "stageTime": "06:42.050",
      "stageDiff": "+00:09.750",
      "totalTime": "17:24.770",
      "totalDiff": "+01:04.411",
      "nationality": "eLngSwedish"
    },
    {
      "rank": 6,
      "name": "rallifan",
      "isVIP": false,
      "isFounder": false,
      "isPlayer": false,
      "isDnfEntry": false,
      "playerDiff": -2,
      "vehicleName": "SUBARU Impreza",
      "stageTime": "06:44.117",
      "stageDiff": "+00:11.817",
      "totalTime": "16:43.923",
      "totalDiff": "+00:23.564",
      "nationality": "eLngSwedish"
    },
    {
      "rank": 7,
      "name": "Mazzan",
      "isVIP": false,
      "isFounder": false,
      "isPlayer": false,
      "isDnfEntry": false,
      "playerDiff": -4,
      "vehicleName": "Ford Focus RS Rally 2007",
      "stageTime": "06:47.350",
      "stageDiff": "+00:15.050",
      "totalTime": "16:45.623",
      "totalDiff": "+00:25.264",
      "nationality": "eLngSwedish"
    },
    {
      "rank": 8,
      "name": "Tastan",
      "isVIP": false,
      "isFounder": false,
      "isPlayer": false,
      "isDnfEntry": false,
      "playerDiff": 2,
      "vehicleName": "SUBARU Impreza",
      "stageTime": "06:48.183",
      "stageDiff": "+00:15.883",
      "totalTime": "17:16.023",
      "totalDiff": "+00:55.664",
      "nationality": "eLngSwedish"
    },
    {
      "rank": 9,
      "name": "johan.nesse",
      "isVIP": false,
      "isFounder": false,
      "isPlayer": false,
      "isDnfEntry": false,
      "playerDiff": 9,
      "vehicleName": "ŠKODA Fabia Rally",
      "stageTime": "06:48.450",
      "stageDiff": "+00:16.150",
      "totalTime": "18:05.914",
      "totalDiff": "+01:45.555",
      "nationality": "eLngSwedish"
    },
    {
      "rank": 10,
      "name": "Rally-Kalle72",
      "isVIP": false,
      "isFounder": false,
      "isPlayer": false,
      "isDnfEntry": false,
      "playerDiff": -1,
      "vehicleName": "ŠKODA Fabia Rally",
      "stageTime": "06:53.550",
      "stageDiff": "+00:21.250",
      "totalTime": "17:17.820",
      "totalDiff": "+00:57.461",
      "nationality": "eLngSwedish"
    },
    {
      "rank": 11,
      "name": "doktor.frojd",
      "isVIP": false,
      "isFounder": false,
      "isPlayer": false,
      "isDnfEntry": false,
      "playerDiff": -5,
      "vehicleName": "Ford Focus RS Rally 2007",
      "stageTime": "06:54.400",
      "stageDiff": "+00:22.100",
      "totalTime": "17:06.333",
      "totalDiff": "+00:45.974",
      "nationality": "eLngSwedish"
    },
    {
      "rank": 12,
      "name": "Dyrran2",
      "isVIP": false,
      "isFounder": false,
      "isPlayer": false,
      "isDnfEntry": false,
      "playerDiff": -4,
      "vehicleName": "SUBARU Impreza",
      "stageTime": "06:58.949",
      "stageDiff": "+00:26.649",
      "totalTime": "17:17.905",
      "totalDiff": "+00:57.546",
      "nationality": "eLngSwedish"
    },
    {
      "rank": 13,
      "name": "rallyrobban81",
      "isVIP": false,
      "isFounder": false,
      "isPlayer": false,
      "isDnfEntry": false,
      "playerDiff": 1,
      "vehicleName": "Ford Focus RS Rally 2007",
      "stageTime": "07:09.299",
      "stageDiff": "+00:36.999",
      "totalTime": "17:51.104",
      "totalDiff": "+01:30.745",
      "nationality": "eLngSwedish"
    },
    {
      "rank": 14,
      "name": "Lialok12",
      "isVIP": false,
      "isFounder": false,
      "isPlayer": false,
      "isDnfEntry": false,
      "playerDiff": -7,
      "vehicleName": "Ford Focus RS Rally 2007",
      "stageTime": "07:11.883",
      "stageDiff": "+00:39.583",
      "totalTime": "17:25.202",
      "totalDiff": "+01:04.843",
      "nationality": "eLngSwedish"
    },
    {
      "rank": 15,
      "name": "Stefan2002",
      "isVIP": false,
      "isFounder": false,
      "isPlayer": false,
      "isDnfEntry": false,
      "playerDiff": -2,
      "vehicleName": "SUBARU Impreza",
      "stageTime": "07:59.116",
      "stageDiff": "+01:26.816",
      "totalTime": "18:37.951",
      "totalDiff": "+02:17.592",
      "nationality": "eLngSwedish"
    },
    {
      "rank": 16,
      "name": "Thomasstriden",
      "isVIP": false,
      "isFounder": false,
      "isPlayer": false,
      "isDnfEntry": false,
      "playerDiff": -11,
      "vehicleName": "ŠKODA Fabia Rally",
      "stageTime": "08:04.597",
      "stageDiff": "+01:32.297",
      "totalTime": "18:04.930",
      "totalDiff": "+01:44.571",
      "nationality": "eLngSwedish"
    },
    {
      "rank": 17,
      "name": "slim2018swe",
      "isVIP": false,
      "isFounder": false,
      "isPlayer": false,
      "isDnfEntry": true,
      "playerDiff": 3,
      "vehicleName": "SUBARU Impreza (2001)",
      "stageTime": "30:00.000",
      "stageDiff": "+23:27.700",
      "totalTime": "01:15:00.000",
      "totalDiff": "+58:39.641",
      "nationality": "eLngSwedish"
    },
    {
      "rank": 18,
      "name": "bjorla78",
      "isVIP": false,
      "isFounder": false,
      "isPlayer": false,
      "isDnfEntry": true,
      "playerDiff": -2,
      "vehicleName": "SUBARU Impreza",
      "stageTime": "30:00.000",
      "stageDiff": "+23:27.700",
      "totalTime": "40:57.189",
      "totalDiff": "+24:36.830",
      "nationality": "eLngSwedish"
    },
    {
      "rank": 19,
      "name": "marko68",
      "isVIP": false,
      "isFounder": false,
      "isPlayer": false,
      "isDnfEntry": true,
      "playerDiff": -2,
      "vehicleName": "ŠKODA Fabia Rally",
      "stageTime": "30:00.000",
      "stageDiff": "+23:27.700",
      "totalTime": "41:15.110",
      "totalDiff": "+24:54.751",
      "nationality": "eLngSwedish"
    },
    {
      "rank": 20,
      "name": "\\\\SWE//",
      "isVIP": false,
      "isFounder": false,
      "isPlayer": false,
      "isDnfEntry": true,
      "playerDiff": -1,
      "vehicleName": "ŠKODA Fabia Rally",
      "stageTime": "30:00.000",
      "stageDiff": "+23:27.700",
      "totalTime": "51:24.493",
      "totalDiff": "+35:04.134",
      "nationality": "eLngSwedish"
    }
  ]
}